proctracer/__init__.py
proctracer/proctracer.py
proctracer/requirements.txt
proctracer/plugins/__init__.py
proctracer/plugins/net_dev.plugin.py
proctracer/plugins/net_snmp_udp.plugin.py
proctracer/plugins/net_softnet_stat.plugin.py
proctracer/plugins/net_udpX.plugin.py
proctracer/plugins/pid_stat.plugin.py
proctracer/plugins/plugin_base.py
proctracer/plugins/plugin_proc_tracer_base.py
proctracer/plugins/pressure_X.plugin.py
proctracer/plugins/stat.plugin.py
proctracer/plugins/text_pipe.plugin.py
proctracer-0.0.32.dist-info/LICENSE.md
proctracer-0.0.32.dist-info/METADATA
proctracer-0.0.32.dist-info/WHEEL
proctracer-0.0.32.dist-info/entry_points.txt
proctracer-0.0.32.dist-info/top_level.txt
proctracer-0.0.32.dist-info/RECORD
