Metadata-Version: 2.1
Name: proctracer
Version: 0.0.32
Summary: /proc Tracer
Home-page: https://github.com/david-kracht/proctracer
Author: David Kracht
Author-email: dave.kracht@gmail.com
License: BSD-3
Project-URL: Documentation, https://github.com/david-kracht/proctracer
Project-URL: Source, https://github.com/david-kracht/proctracer.git
Project-URL: Tracker, https://github.com/david-kracht/proctracer/issues
Keywords: package,proc ,trace
Classifier: Programming Language :: Python :: 3
Classifier: Programming Language :: Python :: 3.6
Classifier: Programming Language :: Python :: 3.7
Classifier: Programming Language :: Python :: 3.8
Requires-Python: >=3.6
License-File: LICENSE.md
Requires-Dist: numexpr >=2.7.3
Requires-Dist: pandas <3.0.0,>=1.3.5
Requires-Dist: matplotlib <4.0.0,>=3.3.4
Requires-Dist: daemonize <3.0.0,>=2.5.0
